layla_focalors/__init__.py
layla_focalors/cyclegan.py
layla_focalors-1.0.0.dist-info/METADATA
layla_focalors-1.0.0.dist-info/WHEEL
layla_focalors-1.0.0.dist-info/top_level.txt
layla_focalors-1.0.0.dist-info/RECORD
